landregistry/healthchecks/__init__.py
landregistry/healthchecks/checks.py
landregistry/healthchecks/dependency.py
landregistry/healthchecks/fakepsy.py
landregistry/healthchecks/healthchecks.py
landregistry/healthchecks/helpers.py
landregistry/healthchecks/py.typed
landregistry_healthchecks-3.0.0.dist-info/METADATA
landregistry_healthchecks-3.0.0.dist-info/WHEEL
landregistry_healthchecks-3.0.0.dist-info/top_level.txt
landregistry_healthchecks-3.0.0.dist-info/RECORD
