Metadata-Version: 2.1
Name: landregistry-healthchecks
Version: 3.0.0
Summary: Standardised health endpoints for HMLR Flask applications
Author: Ian Harvey
Author-email: ian.harvey@landregistry.gov.uk
License: MIT
Requires-Python: >=3.9
Requires-Dist: flask >=2.3.0
Requires-Dist: requests >=2.23.0
